restsh/__init__.py
restsh/__main__.py
restsh/debug.py
restsh/describe.py
restsh/environment.py
restsh/evaluate.py
restsh/module.py
restsh/moduleUtils.py
restsh/parser.py
restsh/py.typed
restsh/reader.py
restsh/repl.py
restsh/service.py
restsh/terminal.py
restsh/token.py
restsh/modules/__init__.py
restsh/modules/builtins.py
restsh/modules/file.py
restsh/modules/http.py
restsh/modules/operators.py
restsh/modules/session.py
restsh/modules/time.py
fa_restsh-1.0.0.dist-info/COPYING
fa_restsh-1.0.0.dist-info/METADATA
fa_restsh-1.0.0.dist-info/WHEEL
fa_restsh-1.0.0.dist-info/entry_points.txt
fa_restsh-1.0.0.dist-info/top_level.txt
fa_restsh-1.0.0.dist-info/RECORD
