Metadata-Version: 2.2
Name: fa-restsh
Version: 1.0.0
Summary: REST and RPC processing, scriptable, shell
Author-email: Ray Wallace III <rwallace3@proton.me>
License: GNU GENERAL PUBLIC LICENSE
Project-URL: Homepage, https://github.com/faboo/restsh
Project-URL: Repository, https://github.com/faboo/restsh.git
Keywords: shell,REST,API,testing
Classifier: Programming Language :: Python :: 3
Classifier: Operating System :: OS Independent
Classifier: Intended Audience :: Developers
Classifier: License :: OSI Approved :: GNU General Public License v2 (GPLv2)
Classifier: Typing :: Typed
Requires-Python: >=3.10
License-File: COPYING
Requires-Dist: pyyaml
Requires-Dist: python-dateutil
Provides-Extra: amqp
Requires-Dist: amqp; extra == "amqp"
Provides-Extra: dev
Requires-Dist: tox; extra == "dev"
Requires-Dist: mypy; extra == "dev"
Requires-Dist: types-PyYAML; extra == "dev"
Requires-Dist: types-python-dateutil; extra == "dev"
Requires-Dist: pylint; extra == "dev"
